mfreport/__init__.py
mfreport/client.py
mfreport/logger.py
mfreport/main.py
mfreport/parser.py
mfreport/writer.py
mfreport/yfwrapper.py
tests/__init__.py
tests/test_main.py
tests/test_parser.py
tests/test_yfwrapper.py
mfreport-0.2.0.dist-info/LICENSE
mfreport-0.2.0.dist-info/METADATA
mfreport-0.2.0.dist-info/WHEEL
mfreport-0.2.0.dist-info/entry_points.txt
mfreport-0.2.0.dist-info/top_level.txt
mfreport-0.2.0.dist-info/RECORD
